<annotation>
	<folder>(1)不同光线情况下透过玻璃进行拍摄</folder>
	<filename>图片 (79).jpg</filename>
	<path>C:\Users\84645\Desktop\人脸识别\人脸识别\人脸识别\(1)不同光线情况下透过玻璃进行拍摄\图片 (79).jpg</path>
	<source>
		<database>Unknown</database>
	</source>
	<size>
		<width>3072</width>
		<height>4096</height>
		<depth>3</depth>
	</size>
	<segmented>0</segmented>
	<object>
		<name>face</name>
		<pose>Unspecified</pose>
		<truncated>0</truncated>
		<difficult>0</difficult>
		<bndbox>
			<xmin>1366</xmin>
			<ymin>1278</ymin>
			<xmax>1940</xmax>
			<ymax>1852</ymax>
		</bndbox>
	</object>
	<object>
		<name>specialarea</name>
		<pose>Unspecified</pose>
		<truncated>0</truncated>
		<difficult>0</difficult>
		<bndbox>
			<xmin>1583</xmin>
			<ymin>1557</ymin>
			<xmax>1723</xmax>
			<ymax>1697</ymax>
		</bndbox>
	</object>
</annotation>
