<annotation>
	<folder>(2）透过不同颜色的玻璃进行拍摄</folder>
	<filename>图片 (76).jpg</filename>
	<path>C:\Users\84645\Desktop\人脸识别\人脸识别\人脸识别\(2）透过不同颜色的玻璃进行拍摄\图片 (76).jpg</path>
	<source>
		<database>Unknown</database>
	</source>
	<size>
		<width>4304</width>
		<height>5760</height>
		<depth>3</depth>
	</size>
	<segmented>0</segmented>
	<object>
		<name>face</name>
		<pose>Unspecified</pose>
		<truncated>0</truncated>
		<difficult>0</difficult>
		<bndbox>
			<xmin>1090</xmin>
			<ymin>1173</ymin>
			<xmax>3550</xmax>
			<ymax>3634</ymax>
		</bndbox>
	</object>
	<object>
		<name>specialarea</name>
		<pose>Unspecified</pose>
		<truncated>0</truncated>
		<difficult>0</difficult>
		<bndbox>
			<xmin>2333</xmin>
			<ymin>1961</ymin>
			<xmax>2933</xmax>
			<ymax>2561</ymax>
		</bndbox>
	</object>
</annotation>
