<annotation>
	<folder>图片</folder>
	<filename>273.jpg</filename>
	<path>C:\Users\84645\Desktop\人脸识别\图片\图片\273.jpg</path>
	<source>
		<database>Unknown</database>
	</source>
	<size>
		<width>960</width>
		<height>640</height>
		<depth>3</depth>
	</size>
	<segmented>0</segmented>
	<object>
		<name>face</name>
		<pose>Unspecified</pose>
		<truncated>0</truncated>
		<difficult>0</difficult>
		<bndbox>
			<xmin>393</xmin>
			<ymin>150</ymin>
			<xmax>607</xmax>
			<ymax>364</ymax>
		</bndbox>
	</object>
	<object>
		<name>specialarea</name>
		<pose>Unspecified</pose>
		<truncated>0</truncated>
		<difficult>0</difficult>
		<bndbox>
			<xmin>482</xmin>
			<ymin>222</ymin>
			<xmax>537</xmax>
			<ymax>277</ymax>
		</bndbox>
	</object>
</annotation>
