<annotation>
	<folder>图片</folder>
	<filename>433.jpg</filename>
	<path>C:\Users\84645\Desktop\人脸识别\图片\图片\433.jpg</path>
	<source>
		<database>Unknown</database>
	</source>
	<size>
		<width>3872</width>
		<height>2592</height>
		<depth>3</depth>
	</size>
	<segmented>0</segmented>
	<object>
		<name>face</name>
		<pose>Unspecified</pose>
		<truncated>0</truncated>
		<difficult>0</difficult>
		<bndbox>
			<xmin>855</xmin>
			<ymin>147</ymin>
			<xmax>3175</xmax>
			<ymax>2467</ymax>
		</bndbox>
	</object>
	<object>
		<name>specialarea</name>
		<pose>Unspecified</pose>
		<truncated>0</truncated>
		<difficult>0</difficult>
		<bndbox>
			<xmin>1804</xmin>
			<ymin>361</ymin>
			<xmax>2407</xmax>
			<ymax>964</ymax>
		</bndbox>
	</object>
</annotation>
