<annotation>
	<folder>图片</folder>
	<filename>508.jpg</filename>
	<path>C:\Users\84645\Desktop\人脸识别\图片\图片\508.jpg</path>
	<source>
		<database>Unknown</database>
	</source>
	<size>
		<width>1200</width>
		<height>800</height>
		<depth>3</depth>
	</size>
	<segmented>0</segmented>
	<object>
		<name>face</name>
		<pose>Unspecified</pose>
		<truncated>0</truncated>
		<difficult>0</difficult>
		<bndbox>
			<xmin>562</xmin>
			<ymin>158</ymin>
			<xmax>1158</xmax>
			<ymax>754</ymax>
		</bndbox>
	</object>
	<object>
		<name>specialarea</name>
		<pose>Unspecified</pose>
		<truncated>0</truncated>
		<difficult>0</difficult>
		<bndbox>
			<xmin>870</xmin>
			<ymin>320</ymin>
			<xmax>1046</xmax>
			<ymax>496</ymax>
		</bndbox>
	</object>
</annotation>
